[
  {
    "date": "2026-03-04",
    "summary": "中東情勢が極めて不安定化。アメリカ・イスラエルとイランの軍事衝突が激化し、周辺国にも波及。ウクライナ情勢への関心低下も懸念される。世界経済への影響も深刻化。",
    "overall_risk_level": "critical",
    "article_count": 10,
    "region_risk_map": {
      "east_asia": "high",
      "southeast_asia": "none",
      "south_asia": "none",
      "central_asia": "none",
      "middle_east": "critical",
      "europe": "medium",
      "africa": "none",
      "north_america": "medium",
      "south_america": "none"
    },
    "generated_at": "2026-03-04T10:33:13.798373"
  }
]